transformation_algebra/__init__.py
transformation_algebra/error.py
transformation_algebra/expr.py
transformation_algebra/py.typed
transformation_algebra/type.py
transformation_algebra-0.1.4.dist-info/LICENSE
transformation_algebra-0.1.4.dist-info/METADATA
transformation_algebra-0.1.4.dist-info/WHEEL
transformation_algebra-0.1.4.dist-info/top_level.txt
transformation_algebra-0.1.4.dist-info/RECORD
